{
    "entity_data": {
        "stonehearth:customization_variants": {
            "packages": {
                "hair_model": {
                    "head_accessory": {
                        "weights": {
                            "[none]": 1,
                            "vox_glasses_0": 1,
                            "vox_goggles_0": 1
                        }
                    },
                    "eyebrows": {
                        "weights": {
                            "[none]": 1,
                            "straight_eyebrows": 1
                        }
                    },
                    "facial_hair": {
                        "weights": {
                            "[none]": 1
                        }
                    }
                }
            }
        }

    }
}